MANIFEST.in
README.md
requirements.txt
setup.cfg
setup.py
reactonite/Config.py
reactonite/Constants.py
reactonite/CreateHtmlCss.py
reactonite/Helpers.py
reactonite/NodeWrapper.py
reactonite/PropsMap.py
reactonite/ReactoniteWatcher.py
reactonite/Transpiler.py
reactonite/__init__.py
reactonite/createHtmlCss.py
reactonite/main.py
reactonite.egg-info/PKG-INFO
reactonite.egg-info/SOURCES.txt
reactonite.egg-info/dependency_links.txt
reactonite.egg-info/entry_points.txt
reactonite.egg-info/requires.txt
reactonite.egg-info/top_level.txt
reactonite/init_src_dir/.gitignore
reactonite/init_src_dir/favicon.ico
reactonite/init_src_dir/features.html
reactonite/init_src_dir/index.html
reactonite/init_src_dir/main.css
reactonite/init_src_dir/main.js
reactonite/init_src_dir/assets/images/reactonite-design.png
reactonite/init_src_dir/assets/images/reactonite-docs.png
reactonite/init_src_dir/assets/images/reactonite-github.png
reactonite/init_src_dir/assets/images/reactonite-html.jpg
reactonite/init_src_dir/assets/images/reactonite-logo.png
reactonite/init_src_dir/assets/images/reactonite-transpiled.jpg
reactonite/init_src_dir/assets/images/wave-footer.svg
reactonite/init_src_dir/assets/images/wave-header.svg
reactonite/init_src_dir/assets/images/wave-hero-background.svg
reactonite/init_src_dir/assets/images/wave-left.svg
reactonite/init_src_dir/assets/images/team/amogh-gulati.jpg
reactonite/init_src_dir/assets/images/team/aniket.jpg
reactonite/init_src_dir/assets/images/team/avi-garg.jpg
reactonite/init_src_dir/assets/images/team/chirag-jain.jpg
reactonite/init_src_dir/assets/images/team/pankaj-jalote.jpg
reactonite/init_src_dir/assets/images/team/saurabh-badhwar.jpg
reactonite/init_src_dir/examples/index.html