Metadata-Version: 2.1
Name: reactonite
Version: 0.1.0
Summary: Transpile HTML to React
Home-page: https://github.com/SDOS2020/Team_3_Reactonite
Author: Reactonite
License: UNKNOWN
Platform: UNKNOWN
Classifier: Programming Language :: Python :: 3
Classifier: Operating System :: OS Independent
Requires-Python: >=3.6
